addok_csv/__init__.py
addok_csv-1.1.0.dist-info/LICENSE
addok_csv-1.1.0.dist-info/METADATA
addok_csv-1.1.0.dist-info/WHEEL
addok_csv-1.1.0.dist-info/entry_points.txt
addok_csv-1.1.0.dist-info/top_level.txt
addok_csv-1.1.0.dist-info/RECORD
