Metadata-Version: 2.1
Name: addok-csv
Version: 1.1.0
Summary: Add CSV support to your Addok instance
Home-page: https://github.com/addok/addok-csv
Keywords: addok,geocoding,csv,plugin
License-File: LICENSE
Provides-Extra: test
Requires-Dist: addok ; extra == 'test'
Requires-Dist: falcon ; extra == 'test'
Requires-Dist: pytest ; extra == 'test'
Requires-Dist: pytest-falcon ; extra == 'test'
